django_dsl/__init__.py
django_dsl/compiler.py
django_dsl/dsl.py
django_dsl/exceptions.py
django_dsl/fields.py
django_dsl/lexer.py
django_dsl/models.py
django_dsl/parser.py
django_dsl/validators.py
django_dsl/locale/pl/LC_MESSAGES/django.mo
django_dsl/locale/pl/LC_MESSAGES/django.po
django_dsl-0.1.12.dist-info/AUTHORS.rst
django_dsl-0.1.12.dist-info/LICENSE
django_dsl-0.1.12.dist-info/METADATA
django_dsl-0.1.12.dist-info/WHEEL
django_dsl-0.1.12.dist-info/top_level.txt
django_dsl-0.1.12.dist-info/RECORD
