Metadata-Version: 2.1
Name: django-dsl
Version: 0.1.12
Summary: DSL for Django ORM
Home-page: https://github.com/mpasternak/django-dsl
Author: Michał Pasternak
Author-email: michal.dtz@gmail.com
License: MIT
Keywords: django-dsl
Classifier: Development Status :: 3 - Alpha
Classifier: Framework :: Django
Classifier: Framework :: Django :: 1.10
Classifier: Intended Audience :: Developers
Classifier: License :: OSI Approved :: BSD License
Classifier: Natural Language :: English
Classifier: Programming Language :: Python :: 3.6
License-File: LICENSE
License-File: AUTHORS.rst
Requires-Dist: ply (>=3.10)
Requires-Dist: Django (>=1.10)
